cu/__init__.py
cu-1.0.2.dist-info/METADATA
cu-1.0.2.dist-info/RECORD
cu-1.0.2.dist-info/WHEEL
cu-1.0.2.dist-info/top_level.txt
