Metadata-Version: 2.1
Name: cu
Version: 1.0.2
Summary: Generate a unique value from a consecutively number list
Home-page: https://abranhe.com
Author: Carlos Abraham
Author-email: abraham@abranhe.com
License: UNKNOWN
Project-URL: Source, https://github.com/abranhe/cu
Platform: UNKNOWN
Classifier: Programming Language :: Python
Classifier: Natural Language :: English
Classifier: Environment :: Plugins
Classifier: Intended Audience :: Developers
Classifier: License :: OSI Approved :: MIT License
Classifier: Programming Language :: Python :: 3
Classifier: Programming Language :: Python :: 3.2
Classifier: Programming Language :: Python :: 3.3
Classifier: Programming Language :: Python :: 3.4
